CHANGES.rst
COPYRIGHT
LICENSE
MANIFEST.in
README.rst
setup.py
gandi_pyramid_prometheus/__init__.py
gandi_pyramid_prometheus/prometheus.py
gandi_pyramid_prometheus/tweenview.py
gandi_pyramid_prometheus/view.py
gandi_pyramid_prometheus.egg-info/PKG-INFO
gandi_pyramid_prometheus.egg-info/SOURCES.txt
gandi_pyramid_prometheus.egg-info/dependency_links.txt
gandi_pyramid_prometheus.egg-info/not-zip-safe
gandi_pyramid_prometheus.egg-info/pbr.json
gandi_pyramid_prometheus.egg-info/requires.txt
gandi_pyramid_prometheus.egg-info/top_level.txt
gandi_pyramid_prometheus/tests/__init__.py
gandi_pyramid_prometheus/tests/base.py
gandi_pyramid_prometheus/tests/test_integration.py
gandi_pyramid_prometheus/tests/test_prometheus.py
gandi_pyramid_prometheus/tests/test_tweenview.py
gandi_pyramid_prometheus/tests/test_view.py