Metadata-Version: 2.1
Name: gandi-pyramid-prometheus
Version: 0.5
Summary: Pyramid Plugin for prometheus integration on multiprocess wsgi server
Home-page: https://github.com/Gandi/gandi-pyramid-prometheus
Author: Gandi
Author-email: feedback@gandi.net
License: BSD-derived (http://www.repoze.org/LICENSE.txt)
Keywords: pyramid prometheus metrics
Platform: UNKNOWN
Classifier: Programming Language :: Python
Classifier: Framework :: Pyramid
Classifier: Topic :: Internet :: WWW/HTTP
Classifier: Topic :: Internet :: WWW/HTTP :: WSGI :: Application
Provides-Extra: test
Provides-Extra: doc
